setup.py
yelppy/__init__.py
yelppy/yelppy.py
yelppy.egg-info/PKG-INFO
yelppy.egg-info/SOURCES.txt
yelppy.egg-info/dependency_links.txt
yelppy.egg-info/not-zip-safe
yelppy.egg-info/requires.txt
yelppy.egg-info/top_level.txt