Metadata-Version: 2.1
Name: yelppy
Version: 0.0.1
Summary: Yelp results
Home-page: UNKNOWN
Author: Goutam Konapala
Author-email: <goutam.iitbbs@gmail.com>
License: UNKNOWN
Platform: UNKNOWN
